timesat_gui/Slide5.JPG
timesat_gui/__init__.py
timesat_gui/__main__.py
timesat_gui/app.py
timesat_gui/file_list_input.py
timesat_gui/tab_data_input.py
timesat_gui/tab_output.py
timesat_gui/tab_run.py
timesat_gui/tab_save_load.py
timesat_gui/tab_settings.py
timesat_gui/ts_full_run.py
timesat_gui/ts_functions.py
timesat_gui/webTIMESAT.py
timesat_gui/static/How to Enable Ask for Download Location in Browsers
timesat_gui/static/LundUniversity_C2line_RGB.png
timesat_gui/static/Slide2.JPG
timesat_gui/static/Slide5.JPG
timesat_gui/static/Slide_flat.jpg
timesat_gui/static/app_home.css
timesat_gui/static/favicon.ico
timesat_gui/static/malmo-university-vector-logo.png
timesat_gui/templates/mainapp.html
timesat_gui-4.1.7.dist-info/METADATA
timesat_gui-4.1.7.dist-info/WHEEL
timesat_gui-4.1.7.dist-info/entry_points.txt
timesat_gui-4.1.7.dist-info/licenses/LICENSE
timesat_gui-4.1.7.dist-info/RECORD
