Metadata-Version: 2.4
Name: timesat-gui
Version: 4.1.7
Summary: Python-based graphical interface and workflow manager for TIMESAT
Author: TIMESAT Team
License: GPL-3.0-only
License-File: LICENSE
Classifier: Environment :: Web Environment
Classifier: Framework :: Flask
Classifier: License :: OSI Approved :: GNU General Public License v3 (GPLv3)
Classifier: Operating System :: OS Independent
Classifier: Programming Language :: Python :: 3
Requires-Python: >=3.10
Requires-Dist: flask>=2.3
Requires-Dist: matplotlib
Requires-Dist: numpy>=1.26
Requires-Dist: pandas
Requires-Dist: pillow
Requires-Dist: plotly
Requires-Dist: psutil
Requires-Dist: pyqt5
Requires-Dist: pyyaml
Requires-Dist: rasterio
Requires-Dist: ray
Requires-Dist: requests>=2.31
Requires-Dist: timesat
